<?xml version="1.0" encoding="utf-8" ?>
<ArrayOfTileType>
  <TileType>
    <ID>0</ID>
    <TextureCoordinate>
      <X>0</X>
      <Y>0</Y>
    </TextureCoordinate>
  </TileType>
  <TileType>
    <ID>1</ID>
    <TextureCoordinate>
      <X>0</X>
      <Y>0</Y>
    </TextureCoordinate>
  </TileType>
  <TileType>
    <ID>2</ID>
    <TextureCoordinate>
      <X>1</X>
      <Y>0</Y>
    </TextureCoordinate>
  </TileType>
  <TileType>
    <ID>3</ID>
    <TextureCoordinate>
      <X>2</X>
      <Y>0</Y>
    </TextureCoordinate>
   </TileType>
    <TileType>
      <ID>4</ID>
      <TextureCoordinate>
        <X>3</X>
        <Y>0</Y>
      </TextureCoordinate>
    </TileType>
  <TileType>
    <ID>5</ID>
    <TextureCoordinate>
      <X>4</X>
      <Y>0</Y>
    </TextureCoordinate>
  </TileType>
  <TileType>
    <ID>6</ID>
    <TextureCoordinate>
      <X>5</X>
      <Y>0</Y>
    </TextureCoordinate>
  </TileType>
  <TileType>
    <ID>7</ID>
    <TextureCoordinate>
      <X>6</X>
      <Y>0</Y>
    </TextureCoordinate>
  </TileType>
  <TileType>
    <ID>8</ID>
    <TextureCoordinate>
      <X>7</X>
      <Y>0</Y>
    </TextureCoordinate>
  </TileType>
  <TileType>
    <ID>9</ID>
    <TextureCoordinate>
      <X>8</X>
      <Y>0</Y>
    </TextureCoordinate>
  </TileType>
  <TileType>
    <ID>10</ID>
    <TextureCoordinate>
      <X>9</X>
      <Y>0</Y>
    </TextureCoordinate>
  </TileType>
  <TileType>
    <ID>11</ID>
    <TextureCoordinate>
      <X>10</X>
      <Y>0</Y>
    </TextureCoordinate>
  </TileType>
  <TileType>
    <ID>12</ID>
    <TextureCoordinate>
      <X>11</X>
      <Y>0</Y>
    </TextureCoordinate>
  </TileType>

</ArrayOfTileType>